tikara/__init__.py
tikara/core.py
tikara/data_types.py
tikara/py.typed
tikara/jars/tika-app-3.0.0.jar
tikara/util/__init__.py
tikara/util/java.py
tikara/util/misc.py
tikara/util/tika.py
tikara-0.1.5.post1.dist-info/METADATA
tikara-0.1.5.post1.dist-info/WHEEL
tikara-0.1.5.post1.dist-info/licenses/LICENSE.txt
tikara-0.1.5.post1.dist-info/RECORD
