Metadata-Version: 2.4
Name: tikara
Version: 0.1.5.post1
Summary: The metadata and text content extractor for almost every file type.
Project-URL: Homepage, https://github.com/baughmann/tikara
Project-URL: Issues, https://github.com/baughmann/tikara/issues
Author-email: Nick Baughman <baughmann1@gmail.com>
License-Expression: Apache-2.0
License-File: LICENSE.txt
Keywords: apache-tika,content-detection,content-extraction,content-indexing,content-intelligence,content-management,content-parsing,content-processing,content-type,data-extraction,data-parsing,data-processing,document-ai,document-analysis,document-automation,document-classification,document-converter,document-extraction,document-indexing,document-intelligence,document-management,document-metadata,document-ocr,document-parsing,document-processing,document-reader,document-text,document-understandi
Classifier: Development Status :: 4 - Beta
Classifier: Framework :: Jupyter
Classifier: Framework :: Pytest
Classifier: Intended Audience :: Developers
Classifier: Intended Audience :: Information Technology
Classifier: Intended Audience :: Science/Research
Classifier: License :: OSI Approved :: Apache Software License
Classifier: Natural Language :: English
Classifier: Operating System :: OS Independent
Classifier: Programming Language :: Java
Classifier: Programming Language :: Python :: 3
Classifier: Programming Language :: Python :: 3.12
Classifier: Topic :: Office/Business
Classifier: Topic :: Scientific/Engineering :: Information Analysis
Classifier: Topic :: Software Development :: Libraries :: Python Modules
Classifier: Topic :: Text Processing
Classifier: Topic :: Text Processing :: General
Classifier: Topic :: Utilities
Requires-Python: >=3.12
Requires-Dist: jpype1>=1.5.1
Requires-Dist: pydantic>=2.10.5
